biobricks/__init__.py
biobricks/api.py
biobricks/auth.py
biobricks/brick.py
biobricks/checks.py
biobricks/cli.py
biobricks/config.py
biobricks/downloader.py
biobricks/dvc_fetcher.py
biobricks/local_bb.py
biobricks/logger.py
biobricks-0.4.0.dist-info/METADATA
biobricks-0.4.0.dist-info/WHEEL
biobricks-0.4.0.dist-info/entry_points.txt
biobricks-0.4.0.dist-info/licenses/LICENSE
biobricks-0.4.0.dist-info/RECORD
