Metadata-Version: 2.4
Name: biobricks
Version: 0.4.0
Summary: Biobricks automates bioinformatics data.
Project-URL: Documentation, https://docs.biobricks.ai
Project-URL: Bug Tracker, https://github.com/biobricks-ai/biobricks/issues
Author-email: Thomas Luechtefeld <tom@insilica.co>, "Jose A. Jaramillo" <jjv@utp.edu.co>
License-File: LICENSE
Classifier: License :: OSI Approved :: MIT License
Classifier: Operating System :: OS Independent
Classifier: Programming Language :: Python :: 3
Requires-Python: >=3.9
Requires-Dist: click>=8.1.3
Requires-Dist: cloup>=3.0.0
Requires-Dist: pyyaml>=6.0.1
Requires-Dist: requests>=2.0.0
Requires-Dist: tqdm>=4.0.0
